Disassembling top-level module in ./mini-tests/not-test.txt
  1       0 LOAD_CONST           x = not ([43m[30m1[39m[49m + 3 == 5)
          3 LOAD_CONST           x = not (1 + [43m[30m3[39m[49m == 5)
          6 BINARY_ADD           x = not ([43m[30m1 + 3[39m[49m == 5)
          7 LOAD_CONST           x = not (1 + 3 == [43m[30m5[39m[49m)
         10 COMPARE_OP           x = not ([43m[30m1 + 3 == 5[39m[49m)
         13 UNARY_NOT            x = [43m[30mnot (1 + 3 == 5[39m[49m)
         14 STORE_NAME           [43m[30mx[39m[49m = not (1 + 3 == 5)
         17 LOAD_CONST           [43m[30mx[39m[49m = not (1 + 3 == 5)
         20 RETURN_VALUE         [43m[30mx[39m[49m = not (1 + 3 == 5)
