Disassembling top-level module in ./opt-v3-tests/john-lambda-lambda.txt
  2       0 LOAD_CONST           [43m[30mdef[39m[49m a(b):
          3 MAKE_FUNCTION        [43m[30mdef[39m[49m a(b):
          6 STORE_NAME           [43m[30mdef[39m[49m a(b):

  5       9 LOAD_NAME            [43m[30ma[39m[49m(lambda a: (lambda b: a, a))
         12 LOAD_CONST           a([43m[30mlambda a: (lambda b: a, a)[39m[49m)
         15 MAKE_FUNCTION        a([43m[30mlambda a: (lambda b: a, a)[39m[49m)
         18 CALL_FUNCTION        [43m[30ma(lambda a: (lambda b: a, a))[39m[49m
         21 POP_TOP              [43m[30ma(lambda a: (lambda b: a, a))[39m[49m
         22 LOAD_CONST           [43m[30ma(lambda a: (lambda b: a, a))[39m[49m
         25 RETURN_VALUE         [43m[30ma(lambda a: (lambda b: a, a))[39m[49m

Disassembling function a
  3       0 LOAD_FAST                a, b = [43m[30mb[39m[49m(3)
          3 LOAD_CONST               a, b = b([43m[30m3[39m[49m)
          6 CALL_FUNCTION            a, b = [43m[30mb(3)[39m[49m
          9 UNPACK_SEQUENCE          [43m[30ma[39m[49m, b = b(3)
         12 STORE_FAST               [43m[30ma[39m[49m, b = b(3)
         15 STORE_FAST               a, [43m[30mb[39m[49m = b(3)
         18 LOAD_CONST               a, [43m[30mb[39m[49m = b(3)
         21 RETURN_VALUE             a, [43m[30mb[39m[49m = b(3)

Disassembling function <lambda>
  5       0 LOAD_CLOSURE         a(lambda a: ([43m[30mlambda b: a[39m[49m, a))
          3 BUILD_TUPLE          a(lambda a: ([43m[30mlambda b: a, a)[39m[49m)
          6 LOAD_CONST           a(lambda a: ([43m[30mlambda b: a[39m[49m, a))
          9 MAKE_CLOSURE         a(lambda a: ([43m[30mlambda b: a[39m[49m, a))
         12 LOAD_DEREF           a(lambda a: (lambda b: a, [43m[30ma[39m[49m))
         15 BUILD_TUPLE          a(lambda a: (lambda b: a, [43m[30ma[39m[49m))
         18 RETURN_VALUE         a(lambda a: (lambda b: a, [43m[30ma[39m[49m))

Disassembling function <lambda>
  5       0 LOAD_DEREF           a(lambda a: (lambda b: [43m[30ma[39m[49m, a))
          3 RETURN_VALUE         a(lambda a: (lambda b: [43m[30ma[39m[49m, a))
