Disassembling top-level module in ./opt-v3-tests/nested-class-test.txt
  1       0 LOAD_CONST           [43m[30mclass[39m[49m A:
          3 BUILD_TUPLE          [43m[30mclass[39m[49m A:
          6 LOAD_CONST           [43m[30mclass[39m[49m A:
          9 MAKE_FUNCTION        [43m[30mclass[39m[49m A:
         12 CALL_FUNCTION        [43m[30mclass[39m[49m A:
         15 BUILD_CLASS          [43m[30mclass[39m[49m A:
         16 STORE_NAME           [43m[30mclass[39m[49m A:

  8      19 LOAD_NAME            a = [43m[30mA[39m[49m()
         22 CALL_FUNCTION        a = [43m[30mA()[39m[49m
         25 STORE_NAME           [43m[30ma[39m[49m = A()

  9      28 LOAD_NAME            b = [43m[30ma[39m[49m.B()
         31 LOAD_ATTR            b = [43m[30ma.B[39m[49m()
         34 CALL_FUNCTION        b = [43m[30ma.B()[39m[49m
         37 STORE_NAME           [43m[30mb[39m[49m = a.B()

 10      40 LOAD_NAME            c = [43m[30mb[39m[49m.C()
         43 LOAD_ATTR            c = [43m[30mb.C[39m[49m()
         46 CALL_FUNCTION        c = [43m[30mb.C()[39m[49m
         49 STORE_NAME           [43m[30mc[39m[49m = b.C()
         52 LOAD_CONST           [43m[30mc[39m[49m = b.C()
         55 RETURN_VALUE         [43m[30mc[39m[49m = b.C()

Disassembling function A
  1       0 LOAD_NAME            [43m[30mclass[39m[49m A:
          3 STORE_NAME           [43m[30mclass[39m[49m A:

  2       6 LOAD_CONST               x = [43m[30m5[39m[49m
          9 STORE_NAME               [43m[30mx[39m[49m = 5

  3      12 LOAD_CONST               [43m[30mclass[39m[49m B:
         15 BUILD_TUPLE              [43m[30mclass[39m[49m B:
         18 LOAD_CONST               [43m[30mclass[39m[49m B:
         21 MAKE_FUNCTION            [43m[30mclass[39m[49m B:
         24 CALL_FUNCTION            [43m[30mclass[39m[49m B:
         27 BUILD_CLASS              [43m[30mclass[39m[49m B:
         28 STORE_NAME               [43m[30mclass[39m[49m B:
         31 LOAD_LOCALS              [43m[30mclass[39m[49m B:
         32 RETURN_VALUE             [43m[30mclass[39m[49m B:

Disassembling function B
  3       0 LOAD_NAME            [43m[30m [39m[49m   class B:
          3 STORE_NAME           [43m[30m [39m[49m   class B:

  4       6 LOAD_CONST                   y = [43m[30m6[39m[49m
          9 STORE_NAME                   [43m[30my[39m[49m = 6

  5      12 LOAD_CONST                   [43m[30mclass[39m[49m C:
         15 BUILD_TUPLE                  [43m[30mclass[39m[49m C:
         18 LOAD_CONST                   [43m[30mclass[39m[49m C:
         21 MAKE_FUNCTION                [43m[30mclass[39m[49m C:
         24 CALL_FUNCTION                [43m[30mclass[39m[49m C:
         27 BUILD_CLASS                  [43m[30mclass[39m[49m C:
         28 STORE_NAME                   [43m[30mclass[39m[49m C:
         31 LOAD_LOCALS                  [43m[30mclass[39m[49m C:
         32 RETURN_VALUE                 [43m[30mclass[39m[49m C:

Disassembling function C
  5       0 LOAD_NAME            [43m[30m [39m[49m       class C:
          3 STORE_NAME           [43m[30m [39m[49m       class C:

  6       6 LOAD_CONST                       z = [43m[30m7[39m[49m
          9 STORE_NAME                       [43m[30mz[39m[49m = 7
         12 LOAD_LOCALS                      [43m[30mz[39m[49m = 7
         13 RETURN_VALUE                     [43m[30mz[39m[49m = 7
