Disassembling top-level module in ./opt-v3-tests/varargs.txt
  2       0 LOAD_CONST           [43m[30mdef[39m[49m f1(a, b, *rest):
          3 MAKE_FUNCTION        [43m[30mdef[39m[49m f1(a, b, *rest):
          6 STORE_NAME           [43m[30mdef[39m[49m f1(a, b, *rest):

  5       9 LOAD_NAME            [43m[30mf1[39m[49m(1, 2)
         12 LOAD_CONST           f1([43m[30m1[39m[49m, 2)
         15 LOAD_CONST           f1(1, [43m[30m2[39m[49m)
         18 CALL_FUNCTION        [43m[30mf1(1, 2)[39m[49m
         21 POP_TOP              [43m[30mf1(1, 2)[39m[49m

  6      22 LOAD_NAME            [43m[30mf1[39m[49m(1, 2, 3, 4, 5, 6, 7)
         25 LOAD_CONST           f1([43m[30m1[39m[49m, 2, 3, 4, 5, 6, 7)
         28 LOAD_CONST           f1(1, [43m[30m2[39m[49m, 3, 4, 5, 6, 7)
         31 LOAD_CONST           f1(1, 2, [43m[30m3[39m[49m, 4, 5, 6, 7)
         34 LOAD_CONST           f1(1, 2, 3, [43m[30m4[39m[49m, 5, 6, 7)
         37 LOAD_CONST           f1(1, 2, 3, 4, [43m[30m5[39m[49m, 6, 7)
         40 LOAD_CONST           f1(1, 2, 3, 4, 5, [43m[30m6[39m[49m, 7)
         43 LOAD_CONST           f1(1, 2, 3, 4, 5, 6, [43m[30m7[39m[49m)
         46 CALL_FUNCTION        [43m[30mf1(1, 2, 3, 4, 5, 6, 7)[39m[49m
         49 POP_TOP              [43m[30mf1(1, 2, 3, 4, 5, 6, 7)[39m[49m

  8      50 LOAD_CONST           [43m[30mdef[39m[49m f2(a, b, **kwrest):
         53 MAKE_FUNCTION        [43m[30mdef[39m[49m f2(a, b, **kwrest):
         56 STORE_NAME           [43m[30mdef[39m[49m f2(a, b, **kwrest):

 11      59 LOAD_NAME            [43m[30mf2[39m[49m(1, 2, name='Bob', age=38)
         62 LOAD_CONST           f2([43m[30m1[39m[49m, 2, name='Bob', age=38)
         65 LOAD_CONST           f2(1, [43m[30m2[39m[49m, name='Bob', age=38)
         68 LOAD_CONST           f2(1, [43m[30m2[39m[49m, name='Bob', age=38)
         71 LOAD_CONST           f2(1, 2, name=[43m[30m'Bob'[39m[49m, age=38)
         74 LOAD_CONST           f2(1, 2, name=[43m[30m'Bob'[39m[49m, age=38)
         77 LOAD_CONST           f2(1, 2, name='Bob', age=[43m[30m38[39m[49m)
         80 CALL_FUNCTION        [43m[30mf2(1, 2, name='Bob', age=38)[39m[49m
         83 POP_TOP              [43m[30mf2(1, 2, name='Bob', age=38)[39m[49m

 13      84 LOAD_CONST           [43m[30mdef[39m[49m f3(a, b, *rest, **kwrest):
         87 MAKE_FUNCTION        [43m[30mdef[39m[49m f3(a, b, *rest, **kwrest):
         90 STORE_NAME           [43m[30mdef[39m[49m f3(a, b, *rest, **kwrest):

 16      93 LOAD_NAME            [43m[30mf3[39m[49m(1, 2, 3, 4, name='Bob', age=38)
         96 LOAD_CONST           f3([43m[30m1[39m[49m, 2, 3, 4, name='Bob', age=38)
         99 LOAD_CONST           f3(1, [43m[30m2[39m[49m, 3, 4, name='Bob', age=38)
        102 LOAD_CONST           f3(1, 2, [43m[30m3[39m[49m, 4, name='Bob', age=38)
        105 LOAD_CONST           f3(1, 2, 3, [43m[30m4[39m[49m, name='Bob', age=38)
        108 LOAD_CONST           f3(1, 2, 3, [43m[30m4[39m[49m, name='Bob', age=38)
        111 LOAD_CONST           f3(1, 2, 3, 4, name=[43m[30m'Bob'[39m[49m, age=38)
        114 LOAD_CONST           f3(1, 2, 3, 4, name=[43m[30m'Bob'[39m[49m, age=38)
        117 LOAD_CONST           f3(1, 2, 3, 4, name='Bob', age=[43m[30m38[39m[49m)
        120 CALL_FUNCTION        [43m[30mf3(1, 2, 3, 4, name='Bob', age=38)[39m[49m
        123 POP_TOP              [43m[30mf3(1, 2, 3, 4, name='Bob', age=38)[39m[49m
        124 LOAD_CONST           [43m[30mf3(1, 2, 3, 4, name='Bob', age=38)[39m[49m
        127 RETURN_VALUE         [43m[30mf3(1, 2, 3, 4, name='Bob', age=38)[39m[49m

Disassembling function f1
  3       0 LOAD_CONST               [43m[30mpass[39m[49m
          3 RETURN_VALUE             [43m[30mpass[39m[49m

Disassembling function f3
 14       0 LOAD_CONST               [43m[30mpass[39m[49m
          3 RETURN_VALUE             [43m[30mpass[39m[49m

Disassembling function f2
  9       0 LOAD_CONST               [43m[30mpass[39m[49m
          3 RETURN_VALUE             [43m[30mpass[39m[49m
